krummstiel/__init__.py
krummstiel/krummstiel.py
krummstiel-0.0.6.dist-info/LICENSE
krummstiel-0.0.6.dist-info/METADATA
krummstiel-0.0.6.dist-info/WHEEL
krummstiel-0.0.6.dist-info/entry_points.txt
krummstiel-0.0.6.dist-info/top_level.txt
krummstiel-0.0.6.dist-info/RECORD
