Metadata-Version: 2.1
Name: krummstiel
Version: 0.0.6
Summary: Backup multiple iOS (iPhone/iPad) devices regularly
Home-page: https://github.com/yoshtec/krummstiel
Author: Yoshtec
Author-email: yoshtec@gmail.com
License: UNKNOWN
Platform: UNKNOWN
Classifier: Programming Language :: Python :: 3
Classifier: License :: OSI Approved :: MIT License
Classifier: Environment :: Console
Classifier: Operating System :: POSIX
Classifier: Operating System :: MacOS
Requires-Python: >=3.5
